.DS_Store
homopy/__init__.py
homopy/elasticity.py
homopy/methods.py
homopy/stiffness_plot.py
homopy/tensor.py
homopy-1.1.0.dist-info/LICENSE
homopy-1.1.0.dist-info/METADATA
homopy-1.1.0.dist-info/WHEEL
homopy-1.1.0.dist-info/top_level.txt
homopy-1.1.0.dist-info/RECORD
