Metadata-Version: 2.1
Name: homopy
Version: 1.1.0
Summary: Your solution for stiffness problems
Home-page: https://github.com/Extraweich/homopy
Author: Nicolas Christ
Author-email: nicolas.christ@kit.edu
Classifier: Programming Language :: Python :: 3
Classifier: License :: OSI Approved :: MIT License
Classifier: Operating System :: OS Independent
License-File: LICENSE
Requires-Dist: numpy
Requires-Dist: matplotlib
Requires-Dist: scipy
